clihelper
