Metadata-Version: 1.0
Name: clihelper
Version: 1.7.6
Summary: Internal Command-Line Application Wrapper
Home-page: https://clihelper.readthedocs.org
Author: Gavin M. Roy
Author-email: gmr@meetme.com
License: UNKNOWN
Platform: UNKNOWN
Classifier: Development Status :: 4 - Beta
Classifier: Intended Audience :: Developers
Classifier: Programming Language :: Python :: 2.6
Classifier: Programming Language :: Python :: 2.7
Classifier: Topic :: Software Development :: Libraries
Classifier: Topic :: Software Development :: Libraries :: Python Modules
Classifier: License :: OSI Approved :: BSD License
